{
  "name": "Akiyama Mizuki - ProSeka (Dark)",
  "colors": {
    "editorBackground": "#141012",
    "editorForeground": "#fbeeff",
    "activityBarBadgeBackground": "#4ba479",
    "sideBarTitleForeground": "#dadada",
    "sideBarBackground": "#141012",
    "titleBarActiveBackground": "#4b2033",
    "titleBarActiveForeground": "#fff",
    "tabActiveBackground": "#4b2033",
    "tabInactiveForeground": "#fff",
    "tabInactiveBackground": "#141012",
    "menuBackground": "#141012",
    "editorGroupHeaderTabsBackground": "#141012",
    "activityBarBackground": "#141012",
    "activityBarForeground": "#ffffff",
    "statusBarBackground": "#13152f",
    "statusBarForeground": "#ffffff",
    "sideBarSectionHeaderBackground": "#141012",
    "titleBarInactiveBackground": "#160f1c",
    "sideBarBorder": "#a95e81",
    "panelBorder": "#a95e81",
    "editorGroupBorder": "#a95e81"
  },
  "tokens": {
    "comment": "#0ee467",
    "variable": "#7cc1f5",
    "color": "#eb8787",
    "invalid": "#D94B64",
    "keyword": "#d7bded",
    "keywordStyle": "",
    "operator": "#ea9ac6",
    "operatorStyle": "bold",
    "tag": "#71f0a0",
    "function": "#4ab7e9",
    "blockVariable": "#4ae9d7",
    "otherVariable": "#f07178",
    "number": "#F78C6C",
    "string": "#dcdcdc",
    "class": "#ea9ac6",
    "inlineCode": "#71f0a0",
    "groovySource": "#ffffff",
    "entityTypes": "#B2CCD6",
    "cssSupport": "#B2CCD6",
    "subMethods": "#FF5370",
    "languageMethods": "#FF5370",
    "entityMethod": "#82AAFF",
    "metaMethod": "#82AAFF",
    "attributes": "#C792EA",
    "htmlAttributes": "#FFCB6B",
    "cssClasses": "#FFCB6B",
    "cssIds": "#82AAFF",
    "inserted": "#C3E88D",
    "deleted": "#FF5370",
    "changed": "#C792EA",
    "regex": "#89DDFF",
    "escape": "#89DDFF",
    "jsonKey0": "#C792EA",
    "jsonKey1": "#FFCB6B",
    "jsonKey2": "#F78C6C",
    "jsonKey3": "#FF5370",
    "jsonKey4": "#C17E70",
    "jsonKey5": "#82AAFF",
    "jsonKey6": "#f07178",
    "jsonKey7": "#C792EA",
    "jsonKey8": "#C3E88D",
    "markdownPlain": "#EEFFFF",
    "markdownRaw": "#C792EA",
    "markdownDollars": "#4ab7e9",
    "markdownDollarsContent": "#7cc1f5",
    "markdownRawPunct": "#65737E",
    "markdownHeading": "#C3E88D",
    "markdownItalic": "#f07178",
    "markdownBold": "#f07178",
    "markdownUnderline": "#F78C6C",
    "markdownBlockquote": "#65737E",
    "markdownLink": "#82AAFF",
    "markdownLinkDesc": "#C792EA",
    "markdownLinkAnchor": "#FFCB6B",
    "markdownRawBlock": "#C792EA",
    "markdownFencedLang": "#65737E",
    "markdownSeparator": "#65737E",
    "markdownTable": "#EEFFFF",
    "groovyForeground": "#4ba479",
    "groovyConstants": "#C792EA",
    "groovyOtherKey": "#ea9ac6",
    "shellShebangMark": "#4ba479",
    "shellShebangContent": "#7cc1f5",
    "shellOption": "#4ab7e9",
    "shellKeywordControl": "#abe40e",
    "rustInterpolation": "#ea9ac6",
    "rustStringCasting": "#ea9ac6",
    "tsKeywordType": "#d7bded",
    "tsAngleBracket": "#dec249"
  }
}
